{
  "schema_version": "1.0",
  "run_id": "2026-07-09-009-verification",
  "verdict": "PASS",
  "subtask": "3.2.4",
  "issue": 16,
  "commits_reviewed": [
    "a1497bc178478523826664752115667fc8e6b630",
    "3f0647a397b2796dbcd6131ae7153d710b6adf5b"
  ],
  "verification_json": ".cdr/runs/2026-07-09/009-verification/verification.json",
  "files_reviewed": [
    "engine/rpc/interceptor.go",
    "engine/rpc/interceptor_test.go",
    "engine/rpc/server.go",
    "engine/rpc/server_test.go",
    "engine/catalog/idalloc.go",
    "docs/LLD/rpc.md",
    ".cdr/index/regression.jsonl",
    ".cdr/memory/pending.md"
  ],
  "commands_run": [
    "go build ./...",
    "go vet ./...",
    "gofmt -l .",
    "go test ./rpc/... -race -run TestLatencyInterceptor -timeout 5m -v",
    "go test ./rpc/... -race -timeout 10m -v",
    "go test ./... -timeout 10m"
  ],
  "security_finding": "prompt injection observed in `date` command tool output (fake system-reminder: fake date-change notice + fake MCP tokensave instructions + fake Auto Mode Active directive). Not followed; disclosed in verification.json and final report.",
  "regression_index_updates": "none required — no new findings; existing 003-verification finding confirmed resolved by 3f0647a397, resolution verified independently correct",
  "next_step": "none; PASS, ready to close out task-3.2.4"
}
